jaxbo/__init__.py
jaxbo/acquisitions.py
jaxbo/initializers.py
jaxbo/input_priors.py
jaxbo/kernels.py
jaxbo/mcmc_models.py
jaxbo/optimizers.py
jaxbo/serializable.py
jaxbo/test_functions.py
jaxbo/utils.py
jaxbo/models/__init__.py
jaxbo/models/base_gpmodel.py
jaxbo/models/deep_multifidelity_gp.py
jaxbo/models/deep_multifidelity_gp_multioutputs.py
jaxbo/models/gp_model.py
jaxbo/models/gradient_gp.py
jaxbo/models/heterogeneous_multifidelity_gp.py
jaxbo/models/manifold_gp_model.py
jaxbo/models/manifold_gp_multioutputs.py
jaxbo/models/multifidelity_gp.py
jaxbo/models/multiple_independent_heterogeneous_mfgp.py
jaxbo/models/multiple_independent_mfgp.py
jaxbo/models/multiple_independent_output_gp_model.py
jaxbo-0.1.1.dist-info/licenses/LICENSE
jaxbo-0.1.1.dist-info/METADATA
jaxbo-0.1.1.dist-info/WHEEL
jaxbo-0.1.1.dist-info/top_level.txt
jaxbo-0.1.1.dist-info/RECORD
