Metadata-Version: 2.4
Name: jaxbo
Version: 0.1.1
Summary: Fork of PredictiveIntelligenceLab/JAX-BO with updates and compatibility improvements for Colab and pipelines
Home-page: https://github.com/ricardogr07/JAX-BO
Download-URL: https://github.com/ricardogr07/JAX-BO
Author: Ricardo García Ramírez
Author-email: rgr.5882@gmail.com
License: Apache 2.0
Project-URL: Source Code, https://github.com/ricardogr07/JAX-BO
Project-URL: Documentation, https://github.com/ricardogr07/JAX-BO
Project-URL: Bug Tracker, https://github.com/ricardogr07/JAX-BO/issues
Keywords: jax,bayesian optimization,machine learning,optimization
Classifier: Programming Language :: Python :: 3.6
Classifier: Programming Language :: Python :: 3.7
Classifier: License :: OSI Approved :: Apache Software License
Classifier: Operating System :: MacOS
Classifier: Operating System :: POSIX :: Linux
Classifier: Topic :: Software Development
Classifier: Topic :: Scientific/Engineering
Classifier: Intended Audience :: Science/Research
Classifier: Intended Audience :: Developers
Requires-Python: >=3.6
License-File: LICENSE
Requires-Dist: numpy
Requires-Dist: scipy
Requires-Dist: jax
Requires-Dist: jaxlib
Requires-Dist: scikit-learn
Requires-Dist: KDEpy
Requires-Dist: pyDOE
Requires-Dist: numpyro
Dynamic: author
Dynamic: author-email
Dynamic: classifier
Dynamic: description
Dynamic: description-content-type
Dynamic: download-url
Dynamic: home-page
Dynamic: keywords
Dynamic: license
Dynamic: license-file
Dynamic: project-url
Dynamic: requires-dist
Dynamic: requires-python
Dynamic: summary
